{
  "status": "ok",
  "api": "Korean Market & Crypto Trends API",
  "endpoint": "/api/v1/trends.json",
  "description": "Hourly South Korea Google Trends topics with related news links.",
  "updated_at": "2026-07-08T14:40:18.386Z",
  "update_frequency": "hourly",
  "source": "Google Trends RSS, geo=KR",
  "count": 10,
  "summary": {
    "total_trending_topics": 10,
    "total_related_news": 30,
    "top_keywords": [
      "삼성중공업",
      "이준영",
      "아들",
      "홀란드",
      "주택담보대출"
    ],
    "traffic": {
      "highest": 5000,
      "average": 1020
    }
  },
  "data": [
    {
      "rank": 1,
      "keyword": "삼성중공업",
      "url": "https://trends.google.com/trending/rss?geo=KR",
      "published_at": "2026-07-08T13:30:00.000Z",
      "approximate_traffic": "500+",
      "approximate_traffic_value": 500,
      "related_news": [
        {
          "title": "삼성중공업, 연간 수주 5년만에 100억달러 돌파",
          "url": "https://www.yna.co.kr/view/AKR20260708078600003",
          "source": "연합뉴스"
        },
        {
          "title": "삼성重, 원유운반선 2척 2849억원 수주",
          "url": "https://v.daum.net/v/20260708113935101",
          "source": "Daum"
        },
        {
          "title": "삼성重, 원유운반선 2척 수주…5년 만 '연간 수주 100억 달러' 돌파",
          "url": "https://www.greened.kr/news/articleView.html?idxno=344569",
          "source": "녹색경제신문"
        }
      ]
    },
    {
      "rank": 2,
      "keyword": "이준영",
      "url": "https://trends.google.com/trending/rss?geo=KR",
      "published_at": "2026-07-08T13:00:00.000Z",
      "approximate_traffic": "500+",
      "approximate_traffic_value": 500,
      "related_news": [
        {
          "title": "'유퀴즈' 이준영 \"유키스 데뷔 후 편의점 알바…매니저와 함께 눈물\"",
          "url": "https://v.daum.net/v/20260708224521281",
          "source": "Daum"
        },
        {
          "title": "'29세' 이준영, 7월 21일 입대 앞둔 솔직 심경...\"갑자기 막 다운돼\" ('유퀴즈')",
          "url": "https://v.daum.net/v/20260708224508280",
          "source": "Daum"
        },
        {
          "title": "이준영, 음주차량 1시간 추격 끝 붙잡아…\"내 차 박아라 생각\" - 머니투데이",
          "url": "https://www.mt.co.kr/entertainment/2026/07/08/2026070818154057491",
          "source": "머니투데이"
        }
      ]
    },
    {
      "rank": 3,
      "keyword": "아들",
      "url": "https://trends.google.com/trending/rss?geo=KR",
      "published_at": "2026-07-08T13:00:00.000Z",
      "approximate_traffic": "200+",
      "approximate_traffic_value": 200,
      "related_news": [
        {
          "title": "차 사주고 양육비 보냈는데…\"결혼 끝나면 보지 말자\" 절연 통보한 아들",
          "url": "https://www.newsis.com/view/NISX20260708_0003700081",
          "source": "뉴시스"
        },
        {
          "title": "\"결혼 때 돈 못 보태면 절연\"…'30대 아들' 통보, 삶의 낙 잃은 아버지 [어떻게 생각하세요]",
          "url": "https://v.daum.net/v/20260708160910898",
          "source": "Daum"
        },
        {
          "title": "차 사줄 땐 \"아빠 최고\"라더니…결혼 앞둔 아들 \"돈 못 보태면 절연\" - 머니투데이",
          "url": "https://www.mt.co.kr/society/2026/07/08/2026070809033748192",
          "source": "머니투데이"
        }
      ]
    },
    {
      "rank": 4,
      "keyword": "홀란드",
      "url": "https://trends.google.com/trending/rss?geo=KR",
      "published_at": "2026-07-08T12:50:00.000Z",
      "approximate_traffic": "1000+",
      "approximate_traffic_value": 1000,
      "related_news": [
        {
          "title": "홀란 최애 머리끈, 시작은 韓기업… 브랜드 ‘끄네끼’는 ‘끈’의 사투리",
          "url": "https://www.donga.com/news/Economy/article/all/20260708/134261082/1",
          "source": "동아일보"
        },
        {
          "title": "\"하루 6끼, 곰처럼 먹는다\"…195cm 괴물 공격수 홀란 이렇게 만들어졌다→6000kcal 폭풍 흡입+생우유·붉은 고기·내장육 위주",
          "url": "https://v.daum.net/v/20260708204137280",
          "source": "Daum"
        },
        {
          "title": "\"다음 월드컵 때 홀란 빌려주세요\" NATO 정상회의에 등장한 홀란의 이름",
          "url": "https://www.nocutnews.co.kr/news/6545132",
          "source": "www.nocutnews.co.kr"
        }
      ]
    },
    {
      "rank": 5,
      "keyword": "주택담보대출",
      "url": "https://trends.google.com/trending/rss?geo=KR",
      "published_at": "2026-07-08T12:00:00.000Z",
      "approximate_traffic": "2000+",
      "approximate_traffic_value": 2000,
      "related_news": [
        {
          "title": "KB국민은행, 주택구입자금 대출 한도 최대 6억→3억 축소",
          "url": "https://www.yna.co.kr/view/AKR20260708153100002",
          "source": "연합뉴스"
        },
        {
          "title": "보험사 주담대 위험계수 상향…가계대출 받기 어려워지나",
          "url": "https://news.einfomax.co.kr/news/articleView.html?idxno=4423854",
          "source": "연합인포맥스"
        },
        {
          "title": "가계대출 급증에 극약처방…“실수요자·2030 직격탄” 우려",
          "url": "https://www.sedaily.com/article/20065448",
          "source": "서울경제신문"
        }
      ]
    },
    {
      "rank": 6,
      "keyword": "류지혁",
      "url": "https://trends.google.com/trending/rss?geo=KR",
      "published_at": "2026-07-08T11:40:00.000Z",
      "approximate_traffic": "500+",
      "approximate_traffic_value": 500,
      "related_news": [
        {
          "title": "프로야구 삼성 류지혁, 주자와 충돌해 교체…어지럼증 호소",
          "url": "https://www.yna.co.kr/view/AKR20260708180900007",
          "source": "연합뉴스"
        },
        {
          "title": "\"류지혁 큰 부상 아니길\" LG도 걱정했다…'어지럼증' 류지혁은 CT 촬영 위해 병원으로",
          "url": "https://v.daum.net/v/20260708222240025",
          "source": "Daum"
        },
        {
          "title": "삼성 류지혁, 수비 중 LG 구본혁과 충돌해 교체…\"어지러움 증세\"",
          "url": "https://www.newsis.com/view/NISX20260708_0003701588",
          "source": "뉴시스"
        }
      ]
    },
    {
      "rank": 7,
      "keyword": "이규혁",
      "url": "https://trends.google.com/trending/rss?geo=KR",
      "published_at": "2026-07-08T11:40:00.000Z",
      "approximate_traffic": "200+",
      "approximate_traffic_value": 200,
      "related_news": [
        {
          "title": "손담비, 속초 가족 여행 공개…17kg 감량 후 바다앞에서 드러낸 한줌 허리 - 조선비즈",
          "url": "https://biz.chosun.com/entertainment/enter_general/2026/07/05/GQ2WMOBRGFQWMN3EMFQTEMZYGM/",
          "source": "Chosunbiz"
        },
        {
          "title": "'이규혁♥' 손담비, 973만 원 명품 가방 메고 속초 나들이 [스타이슈]",
          "url": "https://www.starnewskorea.com/star/2026/07/06/2026070611053649184",
          "source": "스타뉴스"
        },
        {
          "title": "손담비, 속초서 뽐낸 늘씬 몸매…♥이규혁과 투샷에 '활짝'",
          "url": "https://v.daum.net/v/BZzytnvm1V",
          "source": "Daum"
        }
      ]
    },
    {
      "rank": 8,
      "keyword": "맥스 할로웨이",
      "url": "https://trends.google.com/trending/rss?geo=KR",
      "published_at": "2026-07-08T11:30:00.000Z",
      "approximate_traffic": "100+",
      "approximate_traffic_value": 100,
      "related_news": [
        {
          "title": "“내가 UFC 베스트 복서야” 맥그리거에게 던진 할로웨이의 한마디",
          "url": "https://v.daum.net/v/7pDl6spXDu",
          "source": "Daum"
        },
        {
          "title": "“맥그리거의 왼손 한방”…애스피널 경기 예측",
          "url": "https://biz.heraldcorp.com/article/10800157",
          "source": "헤럴드경제"
        },
        {
          "title": "\"맥그리거 피니시? 100% 가능\"…'아들' 지지한 챔피언 볼카노프스키",
          "url": "https://sports.news.nate.com/view/20260707n07881",
          "source": "네이트"
        }
      ]
    },
    {
      "rank": 9,
      "keyword": "이다인",
      "url": "https://trends.google.com/trending/rss?geo=KR",
      "published_at": "2026-07-08T11:20:00.000Z",
      "approximate_traffic": "5000+",
      "approximate_traffic_value": 5000,
      "related_news": [
        {
          "title": "이승기-이다인 부부 7일 둘째 득남…\"산모와 아이 건강\"",
          "url": "https://www.yna.co.kr/view/AKR20260708165300005",
          "source": "연합뉴스"
        },
        {
          "title": "이승기·이다인 둘째 낳았다…\"산모·아이 모두 건강\"",
          "url": "https://www.newsis.com/view/NISX20260708_0003701493",
          "source": "뉴시스"
        },
        {
          "title": "이승기·이다인 부부, 득남…두 아이 부모 됐다 - 머니투데이",
          "url": "https://www.mt.co.kr/entertainment/2026/07/08/2026070820370843076",
          "source": "머니투데이"
        }
      ]
    },
    {
      "rank": 10,
      "keyword": "경주ic",
      "url": "https://trends.google.com/trending/rss?geo=KR",
      "published_at": "2026-07-08T11:20:00.000Z",
      "approximate_traffic": "200+",
      "approximate_traffic_value": 200,
      "related_news": [
        {
          "title": "음주운전 승용차가 탱크로리에 '쾅'...경부고속도로 곳곳 사고",
          "url": "https://www.ytn.co.kr/_ln/0115_202607082045409555",
          "source": "YTN"
        },
        {
          "title": "탱크로리 전도로 기름 유출…3시간 만에 통행 재개",
          "url": "https://www.yonhapnewstv.co.kr/news/AKR202607081022380hH",
          "source": "연합뉴스TV"
        },
        {
          "title": "경부고속도로 교통사고로 경주IC→서경주IC 부분 통제",
          "url": "https://v.daum.net/v/4xxBF9jJ1i",
          "source": "Daum"
        }
      ]
    }
  ]
}
