{
  "status": "ok",
  "endpoint": "/api/v1/trends.json",
  "updated_at": "2026-05-19T13:28:00.361Z",
  "count": 10,
  "data": [
    {
      "rank": 1,
      "keyword": "구조조정",
      "url": "https://trends.google.com/trending/rss?geo=KR",
      "published_at": "2026-05-19T12:20:00.000Z",
      "approximate_traffic": "200+"
    },
    {
      "rank": 2,
      "keyword": "오십프로",
      "url": "https://trends.google.com/trending/rss?geo=KR",
      "published_at": "2026-05-19T12:20:00.000Z",
      "approximate_traffic": "500+"
    },
    {
      "rank": 3,
      "keyword": "재혼",
      "url": "https://trends.google.com/trending/rss?geo=KR",
      "published_at": "2026-05-19T12:10:00.000Z",
      "approximate_traffic": "500+"
    },
    {
      "rank": 4,
      "keyword": "취사병",
      "url": "https://trends.google.com/trending/rss?geo=KR",
      "published_at": "2026-05-19T12:00:00.000Z",
      "approximate_traffic": "200+"
    },
    {
      "rank": 5,
      "keyword": "음료",
      "url": "https://trends.google.com/trending/rss?geo=KR",
      "published_at": "2026-05-19T12:00:00.000Z",
      "approximate_traffic": "200+"
    },
    {
      "rank": 6,
      "keyword": "내일 날씨",
      "url": "https://trends.google.com/trending/rss?geo=KR",
      "published_at": "2026-05-19T11:50:00.000Z",
      "approximate_traffic": "200000+"
    },
    {
      "rank": 7,
      "keyword": "한국 영화",
      "url": "https://trends.google.com/trending/rss?geo=KR",
      "published_at": "2026-05-19T11:50:00.000Z",
      "approximate_traffic": "1000+"
    },
    {
      "rank": 8,
      "keyword": "이자율",
      "url": "https://trends.google.com/trending/rss?geo=KR",
      "published_at": "2026-05-19T11:50:00.000Z",
      "approximate_traffic": "200+"
    },
    {
      "rank": 9,
      "keyword": "배영만",
      "url": "https://trends.google.com/trending/rss?geo=KR",
      "published_at": "2026-05-19T11:50:00.000Z",
      "approximate_traffic": "100+"
    },
    {
      "rank": 10,
      "keyword": "thời tiết ngày mai",
      "url": "https://trends.google.com/trending/rss?geo=KR",
      "published_at": "2026-05-19T11:30:00.000Z",
      "approximate_traffic": "2000+"
    }
  ]
}