{
  "status": "ok",
  "api": "Korean Market & Crypto Trends API",
  "endpoint": "/api/v1/trends.json",
  "description": "Hourly South Korea Google Trends topics with related news links.",
  "updated_at": "2026-06-26T19:53:56.868Z",
  "update_frequency": "hourly",
  "source": "Google Trends RSS, geo=KR",
  "count": 10,
  "summary": {
    "total_trending_topics": 10,
    "total_related_news": 30,
    "top_keywords": [
      "세네갈 대 이라크",
      "norway vs france",
      "노르웨이 대 프랑스",
      "우루과이 축구 국가대표팀",
      "베이징"
    ],
    "traffic": {
      "highest": 10000,
      "average": 2040
    }
  },
  "data": [
    {
      "rank": 1,
      "keyword": "세네갈 대 이라크",
      "url": "https://trends.google.com/trending/rss?geo=KR",
      "published_at": "2026-06-26T18:50:00.000Z",
      "approximate_traffic": "200+",
      "approximate_traffic_value": 200,
      "related_news": [
        {
          "title": "'홍명보호 청천벽력' 끔찍한 예측 나왔다…美 유력지 \"세네갈이 이라크 4-1 대파할 것\"→韓 32강행 확률 폭락하나 [2026 월드컵]",
          "url": "https://v.daum.net/v/20260627011651536",
          "source": "Daum"
        },
        {
          "title": "세네갈이냐 이라크냐…홍명보호 운명, 토론토에서 갈린다",
          "url": "https://biz.heraldcorp.com/article/10790003",
          "source": "헤럴드경제"
        },
        {
          "title": "'홍명보호 초비상' 한국 진짜 32강 못 가나…세네갈, 전반 4분 만에 첫 골…세네갈 대승하면 한국보다 앞선다",
          "url": "https://www.chosun.com/sports/world-football/2026/06/27/MFSGMNRZMUYDON3DMQYGMNZUGQ/",
          "source": "조선일보"
        }
      ]
    },
    {
      "rank": 2,
      "keyword": "norway vs france",
      "url": "https://trends.google.com/trending/rss?geo=KR",
      "published_at": "2026-06-26T18:10:00.000Z",
      "approximate_traffic": "500+",
      "approximate_traffic_value": 500,
      "related_news": [
        {
          "title": "Norway vs France LIVE: FIFA World Cup Group I score, lineups, commentary & updates",
          "url": "https://www.bbc.com/sport/football/live/cn0vrj5rn7kt",
          "source": "BBC"
        },
        {
          "title": "Sources: Norway's Erling Haaland to miss France World Cup clash",
          "url": "https://www.espn.com/soccer/story/_/id/49188052/norway-erling-haaland-miss-france-world-cup-clash-sources",
          "source": "ESPN"
        },
        {
          "title": "Best World Cup Goal Scorer Bets Today (Bet on Kylian Mbappe at Plus-Money)",
          "url": "https://www.si.com/betting/best-world-cup-goal-scorer-bets-today-bet-on-kylian-mbappe-at-plus-money-01kvxm79ja1d",
          "source": "Sports Illustrated"
        }
      ]
    },
    {
      "rank": 3,
      "keyword": "노르웨이 대 프랑스",
      "url": "https://trends.google.com/trending/rss?geo=KR",
      "published_at": "2026-06-26T18:00:00.000Z",
      "approximate_traffic": "5000+",
      "approximate_traffic_value": 5000,
      "related_news": [
        {
          "title": "멀티골에 멀티골로 응수‥드디어 만난 '음바페vs홀란'",
          "url": "https://imnews.imbc.com/replay/2026/nwdesk/article/6833218_37004.html",
          "source": "MBC 뉴스"
        },
        {
          "title": "'음바페 VS 홀란' 세기의 월드컵 맞대결 불발, 프랑스전에서 홀란 벤치행…노르웨이 감독 \"조 1위보다 32강 더 중요\"",
          "url": "https://www.chosun.com/sports/world-football/2026/06/27/MQ2DGYJVGJQWGYTCG5QWMNLFGY/",
          "source": "조선일보"
        },
        {
          "title": "음홀 대전 불발? ‘음바페 선발·홀란드 벤치’ 출발",
          "url": "https://biz.heraldcorp.com/article/10790008",
          "source": "헤럴드경제"
        }
      ]
    },
    {
      "rank": 4,
      "keyword": "우루과이 축구 국가대표팀",
      "url": "https://trends.google.com/trending/rss?geo=KR",
      "published_at": "2026-06-26T17:40:00.000Z",
      "approximate_traffic": "1000+",
      "approximate_traffic_value": 1000,
      "related_news": [
        {
          "title": "'한국에 약간의 호재' 韓 32강 위해 져야 하는 우루과이, 비엘사 감독 향한 항명 사태 발발",
          "url": "https://v.daum.net/v/UFsQRdcnhU",
          "source": "Daum"
        },
        {
          "title": "스페인전 앞두고 내분설 터졌다…우루과이 선수단, 비엘사 감독에 반기 \"훈련·전술 바꿔달라\"",
          "url": "https://www.chosun.com/sports/world-football/2026/06/26/GZSTEZDCG43TEYJXGEZTQM3CHE/",
          "source": "조선일보"
        },
        {
          "title": "[AI프리뷰] 2026 월드컵 27일 H조 우루과이-스페인전, '닥공' 비엘사 첫 승 챙기나",
          "url": "https://www.newspim.com/news/view/20260626000902",
          "source": "뉴스핌"
        }
      ]
    },
    {
      "rank": 5,
      "keyword": "베이징",
      "url": "https://trends.google.com/trending/rss?geo=KR",
      "published_at": "2026-06-26T16:10:00.000Z",
      "approximate_traffic": "500+",
      "approximate_traffic_value": 500,
      "related_news": [
        {
          "title": "소형 비행기, 베이징 초고층 빌딩 충돌···현장서 잔해 낙하",
          "url": "https://www.khan.co.kr/article/202606262140001",
          "source": "경향신문"
        },
        {
          "title": "\"中베이징 108층 最高빌딩에 경비행기 충돌\"…주변 통제·대피",
          "url": "https://v.daum.net/v/20260626231705345",
          "source": "Daum"
        },
        {
          "title": "\"중국 베이징 108층 최고층 건물에 경비행기 충돌\"",
          "url": "https://www.hankookilbo.com/news/article/A2026062623030001481",
          "source": "한국일보"
        }
      ]
    },
    {
      "rank": 6,
      "keyword": "강선우",
      "url": "https://trends.google.com/trending/rss?geo=KR",
      "published_at": "2026-06-26T16:00:00.000Z",
      "approximate_traffic": "500+",
      "approximate_traffic_value": 500,
      "related_news": [
        {
          "title": "강선우 재판서 \"김경, 김병기에 쇼핑백 전달\" 취지 증언",
          "url": "https://www.yna.co.kr/view/AKR20260626171300004",
          "source": "연합뉴스"
        },
        {
          "title": "“김병기 쇼핑백 들고 있었다”…강선우 재판서 전직 보좌진 증언 파장",
          "url": "https://v.daum.net/v/20260626234817627",
          "source": "Daum"
        },
        {
          "title": "[단독] 강선우 ‘1억 공천헌금’ 재판서 “김경, 김병기에게도 쇼핑백” 증언 나와",
          "url": "https://www.hani.co.kr/arti/society/society_general/1265580.html",
          "source": "한겨레"
        }
      ]
    },
    {
      "rank": 7,
      "keyword": "현대 아반떼",
      "url": "https://trends.google.com/trending/rss?geo=KR",
      "published_at": "2026-06-26T16:00:00.000Z",
      "approximate_traffic": "10000+",
      "approximate_traffic_value": 10000,
      "related_news": [
        {
          "title": "다목적 전기차 ‘PV5’ 7인승 확장[부산모빌리티쇼 현장]",
          "url": "https://v.daum.net/v/20260626223400902",
          "source": "Daum"
        },
        {
          "title": "‘각진 국민차’로 안방지킨 현대차…‘3000만원대 SUV’로 선전포고한 BYD",
          "url": "https://www.donga.com/news/Economy/article/all/20260626/134189106/1",
          "source": "동아일보"
        },
        {
          "title": "디 올 뉴 아반떼 최초 공개…부산모빌리티쇼 개막",
          "url": "https://www.yna.co.kr/view/IPT20260626000004365",
          "source": "연합뉴스"
        }
      ]
    },
    {
      "rank": 8,
      "keyword": "박지현",
      "url": "https://trends.google.com/trending/rss?geo=KR",
      "published_at": "2026-06-26T15:50:00.000Z",
      "approximate_traffic": "200+",
      "approximate_traffic_value": 200,
      "related_news": [
        {
          "title": "'나혼산' 박지현, 코쿤에 패션 도움 요청…기안84 질투심 폭발",
          "url": "https://v.daum.net/v/20260627001945020",
          "source": "Daum"
        },
        {
          "title": "'나 혼자 산다' 박지현, 한남동 빈티지 숍 방문…스타일 변신",
          "url": "https://news.nate.com/view/20260626n31365",
          "source": "네이트"
        },
        {
          "title": "기안84, 코드쿤스트 패션 선망하는 박지현에 질투 폭발 “내 자리였어야”(나혼산)",
          "url": "https://m.newsen.com/news_view.php?uid=202606262001136110",
          "source": "뉴스엔"
        }
      ]
    },
    {
      "rank": 9,
      "keyword": "김연아",
      "url": "https://trends.google.com/trending/rss?geo=KR",
      "published_at": "2026-06-26T14:50:00.000Z",
      "approximate_traffic": "2000+",
      "approximate_traffic_value": 2000,
      "related_news": [
        {
          "title": "김연아 “♥고우림과 어떻게하면 오래 좋은 관계 이어갈지 고민”",
          "url": "https://sports.khan.co.kr/article/202606261644003",
          "source": "스포츠경향"
        },
        {
          "title": "김연아, 결혼 후 더 깊어진 여유…“서로 배려하며 살아가” [화보]",
          "url": "https://v.daum.net/v/20260626163051393",
          "source": "Daum"
        },
        {
          "title": "김연아, 강철 멘탈 비결 \"나만의 목표 잡아, 늘 100% 확신 없었다\"",
          "url": "https://www.chosun.com/entertainments/broadcast/2026/06/26/G44DOZLGG5QWGZLGMFSTAYRVMU/",
          "source": "조선일보"
        }
      ]
    },
    {
      "rank": 10,
      "keyword": "백화점",
      "url": "https://trends.google.com/trending/rss?geo=KR",
      "published_at": "2026-06-26T14:40:00.000Z",
      "approximate_traffic": "500+",
      "approximate_traffic_value": 500,
      "related_news": [
        {
          "title": "마트도 백화점도 '반값'…주말 할인대전 열린다",
          "url": "https://v.daum.net/v/20260626181801900",
          "source": "Daum"
        },
        {
          "title": "신세계면세점, 여름 맞아 최대 65% 할인 행사",
          "url": "https://www.yna.co.kr/view/AKR20260626080300030",
          "source": "연합뉴스"
        },
        {
          "title": "백화점 3사, 26일부터 여름 정기 세일 돌입",
          "url": "https://mobile.newsis.com/photo/NISI20260626_0021337907",
          "source": "뉴시스"
        }
      ]
    }
  ]
}
